opylogger.py
opy_logger-2.1.dist-info/LICENSE
opy_logger-2.1.dist-info/METADATA
opy_logger-2.1.dist-info/WHEEL
opy_logger-2.1.dist-info/entry_points.txt
opy_logger-2.1.dist-info/top_level.txt
opy_logger-2.1.dist-info/RECORD
