Metadata-Version: 2.1
Name: opy-logger
Version: 2.1
Summary: Used for simple log output.
Home-page: https://github.com/muhammedcamsari/opy-logger
Author: Muhammed Çamsarı
Author-email: Muhammedcamsari@icloud.com
License: MIT
Keywords: log,logger,simple
Platform: UNKNOWN
Classifier: Programming Language :: Python :: 3
Classifier: License :: OSI Approved :: MIT License
Classifier: Natural Language :: Turkish
Classifier: Operating System :: OS Independent
